{"utilisateur_sourceAdomaine":"C1383$@DOM1","ordinateur_sourceANDsucces_echec":"C1383, Success","poids":24}
{"utilisateur_sourceAdomaine":"C2951$@DOM1","ordinateur_sourceANDsucces_echec":"C2951, Success","poids":24}
{"utilisateur_sourceAdomaine":"C1972$@DOM1","ordinateur_sourceANDsucces_echec":"C25879, Success","poids":24}
{"utilisateur_sourceAdomaine":"C1340$@DOM1","ordinateur_sourceANDsucces_echec":"C1340, Success","poids":24}
{"utilisateur_sourceAdomaine":"C1133$@DOM1","ordinateur_sourceANDsucces_echec":"C1133, Success","poids":24}
{"utilisateur_sourceAdomaine":"C3039$@DOM1","ordinateur_sourceANDsucces_echec":"C3039, Success","poids":24}
{"utilisateur_sourceAdomaine":"C33$@DOM1","ordinateur_sourceANDsucces_echec":"C33, Success","poids":24}
{"utilisateur_sourceAdomaine":"C2740$@DOM1","ordinateur_sourceANDsucces_echec":"C2740, Success","poids":24}
{"utilisateur_sourceAdomaine":"C3307$@DOM1","ordinateur_sourceANDsucces_echec":"C3307, Success","poids":24}
{"utilisateur_sourceAdomaine":"C3327$@DOM1","ordinateur_sourceANDsucces_echec":"C3327, Success","poids":24}
{"utilisateur_sourceAdomaine":"C3822$@DOM1","ordinateur_sourceANDsucces_echec":"C3822, Success","poids":24}
{"utilisateur_sourceAdomaine":"C4545$@DOM1","ordinateur_sourceANDsucces_echec":"C4545, Success","poids":24}
{"utilisateur_sourceAdomaine":"C431$@DOM1","ordinateur_sourceANDsucces_echec":"C431, Success","poids":24}
{"utilisateur_sourceAdomaine":"C108$@DOM1","ordinateur_sourceANDsucces_echec":"C108, Success","poids":24}
{"utilisateur_sourceAdomaine":"C3808$@DOM1","ordinateur_sourceANDsucces_echec":"C3808, Success","poids":24}
{"utilisateur_sourceAdomaine":"C1154$@DOM1","ordinateur_sourceANDsucces_echec":"C1154, Success","poids":24}
{"utilisateur_sourceAdomaine":"C4421$@DOM1","ordinateur_sourceANDsucces_echec":"C4421, Success","poids":24}
{"utilisateur_sourceAdomaine":"C4123$@DOM1","ordinateur_sourceANDsucces_echec":"C4123, Success","poids":24}
{"utilisateur_sourceAdomaine":"C1414$@DOM1","ordinateur_sourceANDsucces_echec":"C1414, Success","poids":24}
{"utilisateur_sourceAdomaine":"C4237$@DOM1","ordinateur_sourceANDsucces_echec":"C4237, Success","poids":24}
{"utilisateur_sourceAdomaine":"C2859$@DOM1","ordinateur_sourceANDsucces_echec":"C2859, Success","poids":24}
{"utilisateur_sourceAdomaine":"C5439$@DOM1","ordinateur_sourceANDsucces_echec":"C5439, Success","poids":24}
{"utilisateur_sourceAdomaine":"C4081$@DOM1","ordinateur_sourceANDsucces_echec":"C4081, Success","poids":24}
{"utilisateur_sourceAdomaine":"C1626$@DOM1","ordinateur_sourceANDsucces_echec":"C1626, Success","poids":24}
{"utilisateur_sourceAdomaine":"C2987$@DOM1","ordinateur_sourceANDsucces_echec":"C2987, Success","poids":24}
{"utilisateur_sourceAdomaine":"C1491$@DOM1","ordinateur_sourceANDsucces_echec":"C1491, Success","poids":24}
{"utilisateur_sourceAdomaine":"C1018$@DOM1","ordinateur_sourceANDsucces_echec":"C1018, Success","poids":24}
{"utilisateur_sourceAdomaine":"C2204$@DOM1","ordinateur_sourceANDsucces_echec":"C2204, Success","poids":24}
{"utilisateur_sourceAdomaine":"C397$@DOM1","ordinateur_sourceANDsucces_echec":"C397, Success","poids":24}
{"utilisateur_sourceAdomaine":"C350$@DOM1","ordinateur_sourceANDsucces_echec":"C350, Success","poids":24}
{"utilisateur_sourceAdomaine":"C558$@DOM1","ordinateur_sourceANDsucces_echec":"C558, Success","poids":24}
{"utilisateur_sourceAdomaine":"C2671$@DOM1","ordinateur_sourceANDsucces_echec":"C2671, Success","poids":24}
{"utilisateur_sourceAdomaine":"C1375$@DOM1","ordinateur_sourceANDsucces_echec":"C1375, Success","poids":24}
{"utilisateur_sourceAdomaine":"C148$@DOM1","ordinateur_sourceANDsucces_echec":"C148, Success","poids":24}
{"utilisateur_sourceAdomaine":"C1475$@DOM1","ordinateur_sourceANDsucces_echec":"C1475, Success","poids":24}
{"utilisateur_sourceAdomaine":"C839$@DOM1","ordinateur_sourceANDsucces_echec":"C839, Success","poids":24}
{"utilisateur_sourceAdomaine":"C1370$@DOM1","ordinateur_sourceANDsucces_echec":"C1370, Success","poids":24}
{"utilisateur_sourceAdomaine":"C2482$@DOM1","ordinateur_sourceANDsucces_echec":"C2482, Success","poids":24}
{"utilisateur_sourceAdomaine":"C5002$@DOM1","ordinateur_sourceANDsucces_echec":"C5002, Success","poids":24}
{"utilisateur_sourceAdomaine":"C1657$@DOM1","ordinateur_sourceANDsucces_echec":"C1657, Success","poids":24}
{"utilisateur_sourceAdomaine":"C1051$@DOM1","ordinateur_sourceANDsucces_echec":"C1051, Success","poids":24}
{"utilisateur_sourceAdomaine":"C3824$@DOM1","ordinateur_sourceANDsucces_echec":"C3824, Success","poids":24}
{"utilisateur_sourceAdomaine":"C5069$@DOM1","ordinateur_sourceANDsucces_echec":"C5069, Success","poids":24}
{"utilisateur_sourceAdomaine":"C650$@DOM1","ordinateur_sourceANDsucces_echec":"C650, Success","poids":24}
{"utilisateur_sourceAdomaine":"C1477$@DOM1","ordinateur_sourceANDsucces_echec":"C1477, Success","poids":24}
{"utilisateur_sourceAdomaine":"C3572$@DOM1","ordinateur_sourceANDsucces_echec":"C3572, Success","poids":24}
{"utilisateur_sourceAdomaine":"C2162$@DOM1","ordinateur_sourceANDsucces_echec":"C2162, Success","poids":24}
{"utilisateur_sourceAdomaine":"C870$@DOM1","ordinateur_sourceANDsucces_echec":"C870, Success","poids":24}
{"utilisateur_sourceAdomaine":"C2672$@DOM1","ordinateur_sourceANDsucces_echec":"C2672, Success","poids":24}
{"utilisateur_sourceAdomaine":"C2854$@DOM1","ordinateur_sourceANDsucces_echec":"C2854, Success","poids":24}
{"utilisateur_sourceAdomaine":"C1224$@DOM1","ordinateur_sourceANDsucces_echec":"C1224, Success","poids":24}
{"utilisateur_sourceAdomaine":"C4353$@DOM1","ordinateur_sourceANDsucces_echec":"C4353, Success","poids":24}
{"utilisateur_sourceAdomaine":"C1824$@DOM1","ordinateur_sourceANDsucces_echec":"C1824, Success","poids":24}
{"utilisateur_sourceAdomaine":"C2321$@DOM1","ordinateur_sourceANDsucces_echec":"C2321, Success","poids":24}
{"utilisateur_sourceAdomaine":"C4468$@DOM1","ordinateur_sourceANDsucces_echec":"C4468, Success","poids":24}
{"utilisateur_sourceAdomaine":"C3134$@DOM1","ordinateur_sourceANDsucces_echec":"C3134, Success","poids":24}
{"utilisateur_sourceAdomaine":"C1388$@DOM1","ordinateur_sourceANDsucces_echec":"C1388, Success","poids":24}
{"utilisateur_sourceAdomaine":"C892$@DOM1","ordinateur_sourceANDsucces_echec":"C892, Success","poids":24}
{"utilisateur_sourceAdomaine":"C2704$@DOM1","ordinateur_sourceANDsucces_echec":"C2704, Success","poids":24}
{"utilisateur_sourceAdomaine":"C97$@DOM1","ordinateur_sourceANDsucces_echec":"C97, Success","poids":24}
{"utilisateur_sourceAdomaine":"C907$@DOM1","ordinateur_sourceANDsucces_echec":"C907, Success","poids":24}
{"utilisateur_sourceAdomaine":"C90$@DOM1","ordinateur_sourceANDsucces_echec":"C90, Success","poids":24}
{"utilisateur_sourceAdomaine":"C140$@DOM1","ordinateur_sourceANDsucces_echec":"C140, Success","poids":24}
{"utilisateur_sourceAdomaine":"C1204$@DOM1","ordinateur_sourceANDsucces_echec":"C1204, Success","poids":24}
{"utilisateur_sourceAdomaine":"C1169$@DOM1","ordinateur_sourceANDsucces_echec":"C1169, Success","poids":24}
{"utilisateur_sourceAdomaine":"C1425$@DOM1","ordinateur_sourceANDsucces_echec":"C1425, Success","poids":24}
{"utilisateur_sourceAdomaine":"C376$@DOM1","ordinateur_sourceANDsucces_echec":"C376, Success","poids":24}
{"utilisateur_sourceAdomaine":"C936$@DOM1","ordinateur_sourceANDsucces_echec":"C936, Success","poids":24}
{"utilisateur_sourceAdomaine":"C841$@DOM1","ordinateur_sourceANDsucces_echec":"C841, Success","poids":24}
{"utilisateur_sourceAdomaine":"U8@DOM1","ordinateur_sourceANDsucces_echec":"C1644, Success","poids":24}
{"utilisateur_sourceAdomaine":"C1111$@DOM1","ordinateur_sourceANDsucces_echec":"C1111, Success","poids":24}
{"utilisateur_sourceAdomaine":"C26$@DOM1","ordinateur_sourceANDsucces_echec":"C26, Success","poids":24}
{"utilisateur_sourceAdomaine":"C783$@DOM1","ordinateur_sourceANDsucces_echec":"C783, Success","poids":24}
{"utilisateur_sourceAdomaine":"C4388$@DOM1","ordinateur_sourceANDsucces_echec":"C4388, Success","poids":24}
{"utilisateur_sourceAdomaine":"C1155$@DOM1","ordinateur_sourceANDsucces_echec":"C1155, Success","poids":24}
{"utilisateur_sourceAdomaine":"C3037$@DOM1","ordinateur_sourceANDsucces_echec":"C3037, Success","poids":24}
{"utilisateur_sourceAdomaine":"C4662$@DOM1","ordinateur_sourceANDsucces_echec":"C4662, Success","poids":24}
{"utilisateur_sourceAdomaine":"C3654$@DOM1","ordinateur_sourceANDsucces_echec":"C3654, Success","poids":24}
{"utilisateur_sourceAdomaine":"C787$@DOM1","ordinateur_sourceANDsucces_echec":"C787, Success","poids":24}
{"utilisateur_sourceAdomaine":"C1009$@DOM1","ordinateur_sourceANDsucces_echec":"C1009, Success","poids":24}
{"utilisateur_sourceAdomaine":"C1545$@DOM1","ordinateur_sourceANDsucces_echec":"C1545, Success","poids":24}
{"utilisateur_sourceAdomaine":"C1186$@DOM1","ordinateur_sourceANDsucces_echec":"C1186, Success","poids":24}
{"utilisateur_sourceAdomaine":"C5594$@DOM1","ordinateur_sourceANDsucces_echec":"C5594, Success","poids":24}
{"utilisateur_sourceAdomaine":"C237$@DOM1","ordinateur_sourceANDsucces_echec":"C237, Success","poids":24}
{"utilisateur_sourceAdomaine":"C2972$@DOM1","ordinateur_sourceANDsucces_echec":"C2972, Success","poids":24}
{"utilisateur_sourceAdomaine":"C4839$@DOM1","ordinateur_sourceANDsucces_echec":"C4839, Success","poids":24}
{"utilisateur_sourceAdomaine":"C737$@DOM1","ordinateur_sourceANDsucces_echec":"C737, Success","poids":24}
{"utilisateur_sourceAdomaine":"C3480$@DOM1","ordinateur_sourceANDsucces_echec":"C3480, Success","poids":24}
{"utilisateur_sourceAdomaine":"C1474$@DOM1","ordinateur_sourceANDsucces_echec":"C1474, Success","poids":24}
{"utilisateur_sourceAdomaine":"C3282$@DOM1","ordinateur_sourceANDsucces_echec":"C3282, Success","poids":24}
{"utilisateur_sourceAdomaine":"C876$@DOM1","ordinateur_sourceANDsucces_echec":"C876, Success","poids":24}
{"utilisateur_sourceAdomaine":"C844$@DOM1","ordinateur_sourceANDsucces_echec":"C844, Success","poids":24}
{"utilisateur_sourceAdomaine":"C2047$@DOM1","ordinateur_sourceANDsucces_echec":"C2047, Success","poids":24}
{"utilisateur_sourceAdomaine":"C896$@DOM1","ordinateur_sourceANDsucces_echec":"C896, Success","poids":24}
{"utilisateur_sourceAdomaine":"C3541$@DOM1","ordinateur_sourceANDsucces_echec":"C3541, Success","poids":24}
{"utilisateur_sourceAdomaine":"C732$@DOM1","ordinateur_sourceANDsucces_echec":"C732, Success","poids":24}
{"utilisateur_sourceAdomaine":"C3237$@DOM1","ordinateur_sourceANDsucces_echec":"C3237, Success","poids":24}
{"utilisateur_sourceAdomaine":"C167$@DOM1","ordinateur_sourceANDsucces_echec":"C167, Success","poids":24}
{"utilisateur_sourceAdomaine":"C2315$@DOM1","ordinateur_sourceANDsucces_echec":"C2315, Success","poids":24}
{"utilisateur_sourceAdomaine":"C1881$@DOM1","ordinateur_sourceANDsucces_echec":"C1881, Success","poids":24}
{"utilisateur_sourceAdomaine":"C3204$@DOM1","ordinateur_sourceANDsucces_echec":"C3204, Success","poids":24}
{"utilisateur_sourceAdomaine":"C242$@DOM1","ordinateur_sourceANDsucces_echec":"C242, Success","poids":24}
{"utilisateur_sourceAdomaine":"C4412$@DOM1","ordinateur_sourceANDsucces_echec":"C4412, Success","poids":24}
{"utilisateur_sourceAdomaine":"C1093$@DOM1","ordinateur_sourceANDsucces_echec":"C1093, Success","poids":24}
{"utilisateur_sourceAdomaine":"C1714$@DOM1","ordinateur_sourceANDsucces_echec":"C1714, Success","poids":24}
{"utilisateur_sourceAdomaine":"C985$@DOM1","ordinateur_sourceANDsucces_echec":"C985, Success","poids":24}
{"utilisateur_sourceAdomaine":"C274$@DOM1","ordinateur_sourceANDsucces_echec":"C274, Success","poids":24}
{"utilisateur_sourceAdomaine":"C71$@DOM1","ordinateur_sourceANDsucces_echec":"C71, Success","poids":24}
{"utilisateur_sourceAdomaine":"C1076$@DOM1","ordinateur_sourceANDsucces_echec":"C1076, Success","poids":24}
{"utilisateur_sourceAdomaine":"C1230$@DOM1","ordinateur_sourceANDsucces_echec":"C1230, Success","poids":24}
{"utilisateur_sourceAdomaine":"C589$@DOM1","ordinateur_sourceANDsucces_echec":"C589, Success","poids":24}
{"utilisateur_sourceAdomaine":"C206$@DOM1","ordinateur_sourceANDsucces_echec":"C206, Success","poids":24}
{"utilisateur_sourceAdomaine":"C1540$@DOM1","ordinateur_sourceANDsucces_echec":"C1540, Success","poids":24}
{"utilisateur_sourceAdomaine":"C102$@DOM1","ordinateur_sourceANDsucces_echec":"C102, Success","poids":24}
{"utilisateur_sourceAdomaine":"C982$@DOM1","ordinateur_sourceANDsucces_echec":"C982, Success","poids":24}
{"utilisateur_sourceAdomaine":"C1460$@DOM1","ordinateur_sourceANDsucces_echec":"C1460, Success","poids":24}
{"utilisateur_sourceAdomaine":"C3959$@DOM1","ordinateur_sourceANDsucces_echec":"C3959, Success","poids":24}
{"utilisateur_sourceAdomaine":"C1110$@DOM1","ordinateur_sourceANDsucces_echec":"C1110, Success","poids":24}
{"utilisateur_sourceAdomaine":"C937$@DOM1","ordinateur_sourceANDsucces_echec":"C937, Success","poids":24}
{"utilisateur_sourceAdomaine":"C2128$@DOM1","ordinateur_sourceANDsucces_echec":"C2128, Success","poids":24}
{"utilisateur_sourceAdomaine":"C531$@DOM1","ordinateur_sourceANDsucces_echec":"C531, Success","poids":24}
{"utilisateur_sourceAdomaine":"C792$@DOM1","ordinateur_sourceANDsucces_echec":"C792, Success","poids":24}
{"utilisateur_sourceAdomaine":"C3826$@DOM1","ordinateur_sourceANDsucces_echec":"C3826, Success","poids":24}
{"utilisateur_sourceAdomaine":"C21$@DOM1","ordinateur_sourceANDsucces_echec":"C21, Success","poids":24}
{"utilisateur_sourceAdomaine":"C709$@DOM1","ordinateur_sourceANDsucces_echec":"C709, Success","poids":24}
{"utilisateur_sourceAdomaine":"C377$@DOM1","ordinateur_sourceANDsucces_echec":"C377, Success","poids":24}
{"utilisateur_sourceAdomaine":"C1077$@DOM1","ordinateur_sourceANDsucces_echec":"C1077, Success","poids":24}
{"utilisateur_sourceAdomaine":"U66@DOM1","ordinateur_sourceANDsucces_echec":"C1881, Success","poids":24}
{"utilisateur_sourceAdomaine":"C935$@DOM1","ordinateur_sourceANDsucces_echec":"C935, Success","poids":24}
{"utilisateur_sourceAdomaine":"C2827$@DOM1","ordinateur_sourceANDsucces_echec":"C2827, Success","poids":24}
{"utilisateur_sourceAdomaine":"C1456$@DOM1","ordinateur_sourceANDsucces_echec":"C1456, Success","poids":24}
{"utilisateur_sourceAdomaine":"C861$@DOM1","ordinateur_sourceANDsucces_echec":"C861, Success","poids":24}
{"utilisateur_sourceAdomaine":"C3894$@DOM1","ordinateur_sourceANDsucces_echec":"C3894, Success","poids":24}
{"utilisateur_sourceAdomaine":"C1195$@DOM1","ordinateur_sourceANDsucces_echec":"C1195, Success","poids":24}
{"utilisateur_sourceAdomaine":"C1604$@DOM1","ordinateur_sourceANDsucces_echec":"C1604, Success","poids":24}
{"utilisateur_sourceAdomaine":"C1322$@DOM1","ordinateur_sourceANDsucces_echec":"C1322, Success","poids":24}
{"utilisateur_sourceAdomaine":"C4603$@DOM1","ordinateur_sourceANDsucces_echec":"C4603, Success","poids":24}
{"utilisateur_sourceAdomaine":"C4271$@DOM1","ordinateur_sourceANDsucces_echec":"C4271, Success","poids":24}
{"utilisateur_sourceAdomaine":"C2507$@DOM1","ordinateur_sourceANDsucces_echec":"C2507, Success","poids":24}
{"utilisateur_sourceAdomaine":"C2835$@DOM1","ordinateur_sourceANDsucces_echec":"C2835, Success","poids":24}
{"utilisateur_sourceAdomaine":"C1796$@DOM1","ordinateur_sourceANDsucces_echec":"C1796, Success","poids":24}
{"utilisateur_sourceAdomaine":"C1857$@DOM1","ordinateur_sourceANDsucces_echec":"C1857, Success","poids":24}
{"utilisateur_sourceAdomaine":"C721$@DOM1","ordinateur_sourceANDsucces_echec":"C721, Success","poids":24}
{"utilisateur_sourceAdomaine":"C168$@DOM1","ordinateur_sourceANDsucces_echec":"C168, Success","poids":24}
{"utilisateur_sourceAdomaine":"C4444$@DOM1","ordinateur_sourceANDsucces_echec":"C4444, Success","poids":24}
{"utilisateur_sourceAdomaine":"C147$@DOM1","ordinateur_sourceANDsucces_echec":"C147, Success","poids":24}
{"utilisateur_sourceAdomaine":"C767$@DOM1","ordinateur_sourceANDsucces_echec":"C767, Success","poids":24}
{"utilisateur_sourceAdomaine":"C1049$@DOM1","ordinateur_sourceANDsucces_echec":"C1049, Success","poids":24}
{"utilisateur_sourceAdomaine":"C4872$@DOM1","ordinateur_sourceANDsucces_echec":"C4872, Success","poids":24}
{"utilisateur_sourceAdomaine":"C1929$@DOM1","ordinateur_sourceANDsucces_echec":"C1929, Success","poids":24}
{"utilisateur_sourceAdomaine":"C1266$@DOM1","ordinateur_sourceANDsucces_echec":"C1266, Success","poids":24}
{"utilisateur_sourceAdomaine":"C3665$@DOM1","ordinateur_sourceANDsucces_echec":"C3665, Success","poids":24}
{"utilisateur_sourceAdomaine":"C821$@DOM1","ordinateur_sourceANDsucces_echec":"C821, Success","poids":24}
{"utilisateur_sourceAdomaine":"C4645$@DOM1","ordinateur_sourceANDsucces_echec":"C4645, Success","poids":24}
{"utilisateur_sourceAdomaine":"C458$@DOM1","ordinateur_sourceANDsucces_echec":"C458, Success","poids":24}
{"utilisateur_sourceAdomaine":"C929$@DOM1","ordinateur_sourceANDsucces_echec":"C17644, Success","poids":24}
{"utilisateur_sourceAdomaine":"C966$@DOM1","ordinateur_sourceANDsucces_echec":"C966, Success","poids":24}
{"utilisateur_sourceAdomaine":"C202$@DOM1","ordinateur_sourceANDsucces_echec":"C202, Success","poids":24}
{"utilisateur_sourceAdomaine":"C1402$@DOM1","ordinateur_sourceANDsucces_echec":"C1402, Success","poids":24}
{"utilisateur_sourceAdomaine":"C3668$@DOM1","ordinateur_sourceANDsucces_echec":"C3668, Success","poids":24}
{"utilisateur_sourceAdomaine":"C1492$@DOM1","ordinateur_sourceANDsucces_echec":"C1492, Success","poids":24}
{"utilisateur_sourceAdomaine":"C4835$@DOM1","ordinateur_sourceANDsucces_echec":"C4835, Success","poids":24}
{"utilisateur_sourceAdomaine":"C905$@DOM1","ordinateur_sourceANDsucces_echec":"C905, Success","poids":24}
{"utilisateur_sourceAdomaine":"C5$@DOM1","ordinateur_sourceANDsucces_echec":"C5, Success","poids":24}
{"utilisateur_sourceAdomaine":"C1539$@DOM1","ordinateur_sourceANDsucces_echec":"C1539, Success","poids":24}
{"utilisateur_sourceAdomaine":"U66@DOM1","ordinateur_sourceANDsucces_echec":"C2344, Success","poids":24}
{"utilisateur_sourceAdomaine":"C763$@DOM1","ordinateur_sourceANDsucces_echec":"C763, Success","poids":24}
{"utilisateur_sourceAdomaine":"C987$@DOM1","ordinateur_sourceANDsucces_echec":"C987, Success","poids":24}
{"utilisateur_sourceAdomaine":"C741$@DOM1","ordinateur_sourceANDsucces_echec":"C741, Success","poids":24}
{"utilisateur_sourceAdomaine":"C1219$@DOM1","ordinateur_sourceANDsucces_echec":"C1219, Success","poids":24}
{"utilisateur_sourceAdomaine":"C4144$@DOM1","ordinateur_sourceANDsucces_echec":"C4144, Success","poids":24}
{"utilisateur_sourceAdomaine":"C1276$@DOM1","ordinateur_sourceANDsucces_echec":"C1276, Success","poids":24}
{"utilisateur_sourceAdomaine":"C1081$@DOM1","ordinateur_sourceANDsucces_echec":"C1081, Success","poids":24}
{"utilisateur_sourceAdomaine":"U7353@C1596","ordinateur_sourceANDsucces_echec":"C1596, Fail","poids":24}
{"utilisateur_sourceAdomaine":"C3024$@DOM1","ordinateur_sourceANDsucces_echec":"C3024, Success","poids":24}
